logdate/__init__.py
logdate/fixed_init_lib.py
logdate/init_lib_old.py
logdate/lca_lib.py
logdate/logD_extend_lib.py
logdate/logD_lib.py
logdate/logD_lib_working.py
logdate/tree_lib.py
logdate/util_lib.py
wLogDate-1.0.2.data/scripts/launch_wLogDate.py
wLogDate-1.0.2.dist-info/LICENSE
wLogDate-1.0.2.dist-info/METADATA
wLogDate-1.0.2.dist-info/WHEEL
wLogDate-1.0.2.dist-info/top_level.txt
wLogDate-1.0.2.dist-info/zip-safe
wLogDate-1.0.2.dist-info/RECORD
